{"success": true, "data": [{"challenge": {"category": "Web", "id": 36, "value": 398, "name": "Internet's Checkpoint 6"}, "user": {"id": 134, "name": "Andrew"}, "date": "2024-09-22T22:20:41.030554+00:00", "team": {"id": 77, "name": "alanisgreen"}, "type": "correct", "id": 7692, "challenge_id": 36}, {"challenge": {"category": "Rev", "id": 14, "value": 436, "name": "SUPERMEGACORP - Day 1"}, "user": {"id": 134, "name": "Andrew"}, "date": "2024-09-22T21:12:05.857814+00:00", "team": {"id": 77, "name": "alanisgreen"}, "type": "correct", "id": 6898, "challenge_id": 14}, {"challenge": {"category": "Misc", "id": 62, "value": 418, "name": "Hidden Cats"}, "user": {"id": 134, "name": "Andrew"}, "date": "2024-09-22T20:12:20.235838+00:00", "team": {"id": 77, "name": "alanisgreen"}, "type": "correct", "id": 5871, "challenge_id": 62}, {"challenge": {"category": "Crypto", "id": 48, "value": 428, "name": "XORcise"}, "user": {"id": 134, "name": "Andrew"}, "date": "2024-09-22T19:56:49.908704+00:00", "team": {"id": 77, "name": "alanisgreen"}, "type": "correct", "id": 5547, "challenge_id": 48}, {"challenge": {"category": "Rev", "id": 9, "value": 392, "name": "Buried in the Sand"}, "user": {"id": 134, "name": "Andrew"}, "date": "2024-09-22T19:00:17.099498+00:00", "team": {"id": 77, "name": "alanisgreen"}, "type": "correct", "id": 4112, "challenge_id": 9}, {"challenge": {"category": "Crypto", "id": 30, "value": 347, "name": "Caesar Salad"}, "user": {"id": 134, "name": "Andrew"}, "date": "2024-09-22T18:51:55.902855+00:00", "team": {"id": 77, "name": "alanisgreen"}, "type": "correct", "id": 3947, "challenge_id": 30}, {"challenge": {"category": "Web", "id": 38, "value": 353, "name": "Internet's Checkpoint 7"}, "user": {"id": 134, "name": "Andrew"}, "date": "2024-09-22T18:23:37.616224+00:00", "team": {"id": 77, "name": "alanisgreen"}, "type": "correct", "id": 3129, "challenge_id": 38}, {"challenge": {"category": "Web", "id": 32, "value": 297, "name": "Internet's Checkpoint 2"}, "user": {"id": 134, "name": "Andrew"}, "date": "2024-09-22T18:17:29.852696+00:00", "team": {"id": 77, "name": "alanisgreen"}, "type": "correct", "id": 2921, "challenge_id": 32}, {"challenge": {"category": "Web", "id": 33, "value": 277, "name": "Internet's Checkpoint 3"}, "user": {"id": 134, "name": "Andrew"}, "date": "2024-09-22T17:23:01.293585+00:00", "team": {"id": 77, "name": "alanisgreen"}, "type": "correct", "id": 905, "challenge_id": 33}, {"challenge": {"category": "Web", "id": 35, "value": 240, "name": "Internet's Checkpoint 4"}, "user": {"id": 134, "name": "Andrew"}, "date": "2024-09-22T17:20:00.744382+00:00", "team": {"id": 77, "name": "alanisgreen"}, "type": "correct", "id": 773, "challenge_id": 35}, {"challenge": {"category": "Web", "id": 39, "value": 301, "name": "Internet's Checkpoint 5"}, "user": {"id": 134, "name": "Andrew"}, "date": "2024-09-22T17:19:42.235544+00:00", "team": {"id": 77, "name": "alanisgreen"}, "type": "correct", "id": 757, "challenge_id": 39}, {"challenge": {"category": "Web", "id": 37, "value": 236, "name": "Internet's Checkpoint 1"}, "user": {"id": 134, "name": "Andrew"}, "date": "2024-09-22T17:18:45.335705+00:00", "team": {"id": 77, "name": "alanisgreen"}, "type": "correct", "id": 715, "challenge_id": 37}, {"challenge": {"category": "Web", "id": 78, "value": 350, "name": "Enron Feedback 1"}, "user": {"id": 134, "name": "Andrew"}, "date": "2024-09-22T17:17:41.485349+00:00", "team": {"id": 77, "name": "alanisgreen"}, "type": "correct", "id": 675, "challenge_id": 78}], "meta": {"count": 13}}
