{"success": true, "data": [{"account_id": 32, "name": "\ud83d\udc3c", "date": "2024-09-22T17:17:54.197331Z", "account_url": "/teams/32"}, {"account_id": 49, "name": "Short-Lived", "date": "2024-09-22T17:18:17.870696Z", "account_url": "/teams/49"}, {"account_id": 89, "name": "VictoriAnna", "date": "2024-09-22T17:18:20.299705Z", "account_url": "/teams/89"}, {"account_id": 97, "name": "pepperjacked", "date": "2024-09-22T17:18:55.380728Z", "account_url": "/teams/97"}, {"account_id": 93, "name": "LeslieChoi", "date": "2024-09-22T17:19:19.075943Z", "account_url": "/teams/93"}, {"account_id": 79, "name": "SparklingStar", "date": "2024-09-22T17:28:49.828827Z", "account_url": "/teams/79"}, {"account_id": 10, "name": "Linger 1109s Boyfriend", "date": "2024-09-22T17:29:05.729201Z", "account_url": "/teams/10"}, {"account_id": 98, "name": "my_little_pwny", "date": "2024-09-22T17:29:17.862722Z", "account_url": "/teams/98"}, {"account_id": 90, "name": "Frog", "date": "2024-09-22T17:31:20.397220Z", "account_url": "/teams/90"}, {"account_id": 61, "name": "GearUp", "date": "2024-09-22T17:33:48.598210Z", "account_url": "/teams/61"}, {"account_id": 88, "name": "Joe_Biden", "date": "2024-09-22T17:43:59.092700Z", "account_url": "/teams/88"}, {"account_id": 102, "name": "Whatever", "date": "2024-09-22T17:44:23.075769Z", "account_url": "/teams/102"}, {"account_id": 117, "name": "AumsTeam", "date": "2024-09-22T17:45:03.498539Z", "account_url": "/teams/117"}, {"account_id": 115, "name": "riverwood02", "date": "2024-09-22T18:01:39.841347Z", "account_url": "/teams/115"}, {"account_id": 109, "name": "Terabyte", "date": "2024-09-22T18:02:08.057697Z", "account_url": "/teams/109"}, {"account_id": 133, "name": "Bobert", "date": "2024-09-22T18:04:07.599445Z", "account_url": "/teams/133"}, {"account_id": 17, "name": "WEZE", "date": "2024-09-22T18:04:10.488814Z", "account_url": "/teams/17"}, {"account_id": 135, "name": "DDDNA", "date": "2024-09-22T18:04:30.615053Z", "account_url": "/teams/135"}, {"account_id": 45, "name": "awsomesauce", "date": "2024-09-22T18:11:20.538968Z", "account_url": "/teams/45"}, {"account_id": 143, "name": "cava", "date": "2024-09-22T18:14:53.369156Z", "account_url": "/teams/143"}, {"account_id": 99, "name": "Bench", "date": "2024-09-22T18:34:59.030035Z", "account_url": "/teams/99"}, {"account_id": 19, "name": "t", "date": "2024-09-22T18:39:16.356351Z", "account_url": "/teams/19"}, {"account_id": 57, "name": "Conpuzzled", "date": "2024-09-22T18:44:19.357234Z", "account_url": "/teams/57"}, {"account_id": 26, "name": "l33t", "date": "2024-09-22T18:53:45.476693Z", "account_url": "/teams/26"}, {"account_id": 75, "name": "RnM", "date": "2024-09-22T19:03:32.860443Z", "account_url": "/teams/75"}, {"account_id": 43, "name": "Full Sync DX+", "date": "2024-09-22T19:18:21.482358Z", "account_url": "/teams/43"}, {"account_id": 59, "name": "jk", "date": "2024-09-22T19:23:32.564519Z", "account_url": "/teams/59"}, {"account_id": 64, "name": "411", "date": "2024-09-22T19:24:58.936238Z", "account_url": "/teams/64"}, {"account_id": 128, "name": "arthurl5", "date": "2024-09-22T19:26:02.266327Z", "account_url": "/teams/128"}, {"account_id": 15, "name": "Raccooooon", "date": "2024-09-22T19:27:15.801530Z", "account_url": "/teams/15"}, {"account_id": 76, "name": "our doubles ditched us", "date": "2024-09-22T19:28:24.295592Z", "account_url": "/teams/76"}, {"account_id": 41, "name": "MaxMSPwny", "date": "2024-09-22T20:02:11.469199Z", "account_url": "/teams/41"}, {"account_id": 140, "name": "supercow team", "date": "2024-09-22T20:05:39.007374Z", "account_url": "/teams/140"}, {"account_id": 11, "name": "Fun With Flags", "date": "2024-09-22T20:08:23.834468Z", "account_url": "/teams/11"}, {"account_id": 30, "name": "od skibini", "date": "2024-09-22T20:17:33.553710Z", "account_url": "/teams/30"}, {"account_id": 18, "name": "WD", "date": "2024-09-22T20:17:55.707948Z", "account_url": "/teams/18"}, {"account_id": 71, "name": "pickle cookies", "date": "2024-09-22T20:24:16.086589Z", "account_url": "/teams/71"}, {"account_id": 31, "name": "we had to change this name", "date": "2024-09-22T20:40:27.344837Z", "account_url": "/teams/31"}, {"account_id": 139, "name": "Team Team", "date": "2024-09-22T20:41:14.191956Z", "account_url": "/teams/139"}, {"account_id": 52, "name": "Linux Users", "date": "2024-09-22T20:47:19.483920Z", "account_url": "/teams/52"}, {"account_id": 145, "name": "Ouroboros", "date": "2024-09-22T20:59:49.472452Z", "account_url": "/teams/145"}, {"account_id": 101, "name": "ah-lp", "date": "2024-09-22T20:59:56.108940Z", "account_url": "/teams/101"}, {"account_id": 154, "name": "lin7sz", "date": "2024-09-22T21:00:42.290921Z", "account_url": "/teams/154"}, {"account_id": 121, "name": "b2sb", "date": "2024-09-22T21:21:00.105224Z", "account_url": "/teams/121"}, {"account_id": 67, "name": "something stupid", "date": "2024-09-22T21:25:10.931794Z", "account_url": "/teams/67"}, {"account_id": 149, "name": "MB3", "date": "2024-09-22T21:40:14.672194Z", "account_url": "/teams/149"}, {"account_id": 39, "name": "caneslovers69", "date": "2024-09-22T21:41:12.465958Z", "account_url": "/teams/39"}, {"account_id": 6, "name": "Forknife", "date": "2024-09-22T21:48:03.040240Z", "account_url": "/teams/6"}, {"account_id": 12, "name": "henneylover2011", "date": "2024-09-22T21:50:22.060410Z", "account_url": "/teams/12"}, {"account_id": 110, "name": "Branch 4", "date": "2024-09-22T21:50:58.405382Z", "account_url": "/teams/110"}, {"account_id": 100, "name": "3 plate squat", "date": "2024-09-22T22:09:23.465486Z", "account_url": "/teams/100"}, {"account_id": 58, "name": "isr_dining", "date": "2024-09-22T22:12:38.258898Z", "account_url": "/teams/58"}, {"account_id": 9, "name": "<||____orz", "date": "2024-09-22T22:15:25.939414Z", "account_url": "/teams/9"}, {"account_id": 82, "name": "Double_B", "date": "2024-09-22T22:17:24.653732Z", "account_url": "/teams/82"}, {"account_id": 22, "name": "M4tcha L4tte", "date": "2024-09-22T22:18:29.117007Z", "account_url": "/teams/22"}, {"account_id": 54, "name": "limes", "date": "2024-09-22T22:22:05.801410Z", "account_url": "/teams/54"}, {"account_id": 84, "name": "ziyangz5", "date": "2024-09-22T22:33:34.729913Z", "account_url": "/teams/84"}, {"account_id": 66, "name": "Arima", "date": "2024-09-22T22:49:08.462529Z", "account_url": "/teams/66"}, {"account_id": 47, "name": "Amit", "date": "2024-09-22T22:54:48.009903Z", "account_url": "/teams/47"}]}
