{"success": true, "data": [{"challenge": {"category": "Misc", "id": 71, "value": 479, "name": "Badge 0 - Connect"}, "user": {"id": 220, "name": "cava"}, "date": "2024-09-22T22:36:04.863589+00:00", "team": {"id": 143, "name": "cava"}, "type": "correct", "id": 7892, "challenge_id": 71}, {"challenge": {"category": "Misc", "id": 62, "value": 418, "name": "Hidden Cats"}, "user": {"id": 220, "name": "cava"}, "date": "2024-09-22T22:35:51.274231+00:00", "team": {"id": 143, "name": "cava"}, "type": "correct", "id": 7888, "challenge_id": 62}, {"challenge": {"category": "OSINT", "id": 3, "value": 482, "name": "swiss transport"}, "user": {"id": 220, "name": "cava"}, "date": "2024-09-22T22:26:46.489892+00:00", "team": {"id": 143, "name": "cava"}, "type": "correct", "id": 7762, "challenge_id": 3}, {"challenge": {"category": "OSINT", "id": 44, "value": 481, "name": "Photography III: Park Hopper"}, "user": {"id": 220, "name": "cava"}, "date": "2024-09-22T22:25:14.307997+00:00", "team": {"id": 143, "name": "cava"}, "type": "correct", "id": 7729, "challenge_id": 44}, {"challenge": {"category": "OSINT", "id": 60, "value": 472, "name": "GitHub's Hidden Gem Hunt"}, "user": {"id": 220, "name": "cava"}, "date": "2024-09-22T22:18:29.330964+00:00", "team": {"id": 143, "name": "cava"}, "type": "correct", "id": 7666, "challenge_id": 60}, {"challenge": {"category": "Pwn", "id": 54, "value": 473, "name": "pwntools"}, "user": {"id": 220, "name": "cava"}, "date": "2024-09-22T22:15:19.656352+00:00", "team": {"id": 143, "name": "cava"}, "type": "correct", "id": 7634, "challenge_id": 54}, {"challenge": {"category": "Web", "id": 78, "value": 350, "name": "Enron Feedback 1"}, "user": {"id": 220, "name": "cava"}, "date": "2024-09-22T20:05:38.350160+00:00", "team": {"id": 143, "name": "cava"}, "type": "correct", "id": 5723, "challenge_id": 78}, {"challenge": {"category": "Web", "id": 49, "value": 369, "name": "Path to Success"}, "user": {"id": 220, "name": "cava"}, "date": "2024-09-22T20:00:28.397535+00:00", "team": {"id": 143, "name": "cava"}, "type": "correct", "id": 5639, "challenge_id": 49}, {"challenge": {"category": "Rev", "id": 46, "value": 469, "name": "Flag Generator"}, "user": {"id": 220, "name": "cava"}, "date": "2024-09-22T19:37:09.812621+00:00", "team": {"id": 143, "name": "cava"}, "type": "correct", "id": 5085, "challenge_id": 46}, {"challenge": {"category": "Rev", "id": 2, "value": 497, "name": "'works on my machine'"}, "user": {"id": 220, "name": "cava"}, "date": "2024-09-22T19:33:54.245207+00:00", "team": {"id": 143, "name": "cava"}, "type": "correct", "id": 5022, "challenge_id": 2}, {"challenge": {"category": "Pwn", "id": 55, "value": 432, "name": "Bug Bounty 1"}, "user": {"id": 220, "name": "cava"}, "date": "2024-09-22T19:29:59.674370+00:00", "team": {"id": 143, "name": "cava"}, "type": "correct", "id": 4926, "challenge_id": 55}, {"challenge": {"category": "OSINT", "id": 43, "value": 356, "name": "Photography I: Anonymous???"}, "user": {"id": 220, "name": "cava"}, "date": "2024-09-22T19:19:26.385417+00:00", "team": {"id": 143, "name": "cava"}, "type": "correct", "id": 4660, "challenge_id": 43}, {"challenge": {"category": "Crypto", "id": 48, "value": 428, "name": "XORcise"}, "user": {"id": 220, "name": "cava"}, "date": "2024-09-22T19:10:06.438105+00:00", "team": {"id": 143, "name": "cava"}, "type": "correct", "id": 4349, "challenge_id": 48}, {"challenge": {"category": "Crypto", "id": 30, "value": 347, "name": "Caesar Salad"}, "user": {"id": 220, "name": "cava"}, "date": "2024-09-22T19:04:21.223850+00:00", "team": {"id": 143, "name": "cava"}, "type": "correct", "id": 4193, "challenge_id": 30}, {"challenge": {"category": "OSINT", "id": 20, "value": 400, "name": "bridge, japan"}, "user": {"id": 220, "name": "cava"}, "date": "2024-09-22T18:49:02.965931+00:00", "team": {"id": 143, "name": "cava"}, "type": "correct", "id": 3865, "challenge_id": 20}, {"challenge": {"category": "OSINT", "id": 61, "value": 316, "name": "The Professor's Request"}, "user": {"id": 220, "name": "cava"}, "date": "2024-09-22T18:42:46.769793+00:00", "team": {"id": 143, "name": "cava"}, "type": "correct", "id": 3710, "challenge_id": 61}, {"challenge": {"category": "Web", "id": 39, "value": 301, "name": "Internet's Checkpoint 5"}, "user": {"id": 220, "name": "cava"}, "date": "2024-09-22T18:38:23.295824+00:00", "team": {"id": 143, "name": "cava"}, "type": "correct", "id": 3600, "challenge_id": 39}, {"challenge": {"category": "Web", "id": 32, "value": 297, "name": "Internet's Checkpoint 2"}, "user": {"id": 220, "name": "cava"}, "date": "2024-09-22T18:37:23.189048+00:00", "team": {"id": 143, "name": "cava"}, "type": "correct", "id": 3571, "challenge_id": 32}, {"challenge": {"category": "Web", "id": 35, "value": 240, "name": "Internet's Checkpoint 4"}, "user": {"id": 220, "name": "cava"}, "date": "2024-09-22T18:31:46.677760+00:00", "team": {"id": 143, "name": "cava"}, "type": "correct", "id": 3416, "challenge_id": 35}, {"challenge": {"category": "Web", "id": 37, "value": 236, "name": "Internet's Checkpoint 1"}, "user": {"id": 220, "name": "cava"}, "date": "2024-09-22T18:31:28.605193+00:00", "team": {"id": 143, "name": "cava"}, "type": "correct", "id": 3405, "challenge_id": 37}, {"challenge": {"category": "Welcome", "id": 65, "value": 447, "name": "REDLattice Sponsor Flag"}, "user": {"id": 220, "name": "cava"}, "date": "2024-09-22T18:23:33.340174+00:00", "team": {"id": 143, "name": "cava"}, "type": "correct", "id": 3125, "challenge_id": 65}, {"challenge": {"category": "Welcome", "id": 69, "value": 456, "name": "UIUC Tech Services Sponsor Flag"}, "user": {"id": 220, "name": "cava"}, "date": "2024-09-22T18:20:50.242844+00:00", "team": {"id": 143, "name": "cava"}, "type": "correct", "id": 3026, "challenge_id": 69}, {"challenge": {"category": "Welcome", "id": 72, "value": 441, "name": "Battelle Sponsor Flag"}, "user": {"id": 220, "name": "cava"}, "date": "2024-09-22T18:14:53.369156+00:00", "team": {"id": 143, "name": "cava"}, "type": "correct", "id": 2822, "challenge_id": 72}, {"challenge": {"category": "Welcome", "id": 68, "value": 285, "name": "Resume Upload"}, "user": {"id": 220, "name": "cava"}, "date": "2024-09-22T18:14:01.971537+00:00", "team": {"id": 143, "name": "cava"}, "type": "correct", "id": 2794, "challenge_id": 68}, {"challenge": {"category": "Welcome", "id": 66, "value": 195, "name": "Welcome to Fall CTF"}, "user": {"id": 220, "name": "cava"}, "date": "2024-09-22T18:13:08.394652+00:00", "team": {"id": 143, "name": "cava"}, "type": "correct", "id": 2770, "challenge_id": 66}], "meta": {"count": 25}}
